{
  "trainingPhrases": [ {
    "parts": [ {
      "text": "A luz online não para de piscar",
      "auto": true
    } ],
    "repeatCount": 1,
    "languageCode": "pt-br"
  }, {
    "parts": [ {
      "text": "A ",
      "auto": true
    }, {
      "text": "luz on-line",
      "auto": true
    }, {
      "text": " não pisca",
      "auto": true
    } ],
    "repeatCount": 1,
    "languageCode": "pt-br"
  }, {
    "parts": [ {
      "text": "Minha internet caiu",
      "auto": true
    } ],
    "repeatCount": 1,
    "languageCode": "pt-br"
  } ]
}
